Workbook

Sheet Raw Data
A1: Order ID | B1: Order Date | C1: Ship Date | D1: Customer Name | E1: Segment | F1: Region | G1: State | H1: City | I1: Category | J1: Sub-Category | K1: Sales | L1: Quantity | M1: Discount | N1: Profit | O1: Order Month
A2: US-2024-1001 | B2: 45324 | C2: 45331 | D2: Susan Johnson | E2: Consumer | F2: East | G2: New York | H2: New York City | I2: Technology | J2: Phones | K2: 1323.44 | L2: 4 | M2: 0 | N2: 331.78 | O2: =TEXT(B2,"mmm-yyyy") -> Feb-2024
A3: US-2025-1002 | B3: 45708 | C3: 45710 | D3: Robert Miller | E3: Corporate | F3: West | G3: Colorado | H3: Denver | I3: Furniture | J3: Furnishings | K3: 162.47 | L3: 7 | M3: 0 | N3: 28.77 | O3: =TEXT(B3,"mmm-yyyy") -> Feb-2025
A4: US-2024-1003 | B4: 45639 | C4: 45646 | D4: John Johnson | E4: Corporate | F4: South | G4: Florida | H4: Miami | I4: Technology | J4: Phones | K4: 3129.68 | L4: 4 | M4: 0 | N4: 335.07 | O4: =TEXT(B4,"mmm-yyyy") -> Dec-2024
A5: US-2024-1004 | B5: 45547 | C5: 45554 | D5: Susan Davis | E5: Corporate | F5: South | G5: Georgia | H5: Atlanta | I5: Office Supplies | J5: Paper | K5: 130.14 | L5: 8 | M5: 0.3 | N5: 40.14 | O5: =TEXT(B5,"mmm-yyyy") -> Sep-2024
A6: US-2024-1005 | B6: 45462 | C6: 45466 | D6: Margaret Martin | E6: Consumer | F6: East | G6: New York | H6: New York City | I6: Technology | J6: Phones | K6: 1295.81 | L6: 4 | M6: 0.3 | N6: 220.69 | O6: =TEXT(B6,"mmm-yyyy") -> Jun-2024
A7: US-2025-1006 | B7: 45757 | C7: 45760 | D7: Anthony Rodriguez | E7: Corporate | F7: East | G7: Pennsylvania | H7: Philadelphia | I7: Office Supplies | J7: Binders | K7: 144.56 | L7: 8 | M7: 0 | N7: 15.46 | O7: =TEXT(B7,"mmm-yyyy") -> Apr-2025
A8: US-2024-1007 | B8: 45350 | C8: 45351 | D8: Betty Hernandez | E8: Corporate | F8: West | G8: California | H8: Los Angeles | I8: Technology | J8: Phones | K8: 1639.65 | L8: 3 | M8: 0 | N8: 554.58 | O8: =TEXT(B8,"mmm-yyyy") -> Feb-2024
A9: US-2025-1008 | B9: 45705 | C9: 45706 | D9: Robert Brown | E9: Consumer | F9: East | G9: Pennsylvania | H9: Philadelphia | I9: Furniture | J9: Chairs | K9: 1936.74 | L9: 4 | M9: 0.15 | N9: 442.27 | O9: =TEXT(B9,"mmm-yyyy") -> Feb-2025
A10: US-2025-1009 | B10: 45977 | C10: 45983 | D10: Thomas Brown | E10: Consumer | F10: East | G10: Massachusetts | H10: Boston | I10: Technology | J10: Accessories | K10: 455 | L10: 5 | M10: 0.1 | N10: 40.61 | O10: =TEXT(B10,"mmm-yyyy") -> Nov-2025
A11: US-2025-1010 | B11: 45928 | C11: 45933 | D11: Lisa Jackson | E11: Corporate | F11: Central | G11: Michigan | H11: Detroit | I11: Office Supplies | J11: Binders | K11: 67.75 | L11: 2 | M11: 0.15 | N11: 7.72 | O11: =TEXT(B11,"mmm-yyyy") -> Sep-2025
A12: US-2024-1011 | B12: 45583 | C12: 45585 | D12: Robert Miller | E12: Corporate | F12: Central | G12: Texas | H12: Houston | I12: Office Supplies | J12: Binders | K12: 79.26 | L12: 5 | M12: 0.15 | N12: 27.36 | O12: =TEXT(B12,"mmm-yyyy") -> Oct-2024
A13: US-2024-1012 | B13: 45410 | C13: 45411 | D13: John Williams | E13: Corporate | F13: East | G13: Virginia | H13: Richmond | I13: Office Supplies | J13: Binders | K13: 90.63 | L13: 3 | M13: 0 | N13: 12.19 | O13: =TEXT(B13,"mmm-yyyy") -> Apr-2024
... A601: US-2024-1600 | B601: 45451 | C601: 45452 | D601: Joseph Jackson | E601: Corporate | F601: East | G601: Massachusetts | H601: Boston | I601: Office Supplies | J601: Paper | K601: 116.69 | L601: 6 | M601: 0.2 | N601: 30.53 | O601: =TEXT(B601,"mmm-yyyy") -> Jun-2024

Sheet Q1 - Sales by Region
A1: Q1: Total Sales and Profit by Region
A3: Region | B3: Total Sales | C3: Total Profit
A4: Central | B4: =SUMIF('Raw Data'!F2:F601,A4,'Raw Data'!K2:K601) -> 208007.97 | C4: =SUMIF('Raw Data'!F2:F601,A4,'Raw Data'!N2:N601) -> 24318.11
A5: East | B5: =SUMIF('Raw Data'!F2:F601,A5,'Raw Data'!K2:K601) -> 278158.44 | C5: =SUMIF('Raw Data'!F2:F601,A5,'Raw Data'!N2:N601) -> 39389.06
A6: South | B6: =SUMIF('Raw Data'!F2:F601,A6,'Raw Data'!K2:K601) -> 256242.38 | C6: =SUMIF('Raw Data'!F2:F601,A6,'Raw Data'!N2:N601) -> 28024.56
A7: West | B7: =SUMIF('Raw Data'!F2:F601,A7,'Raw Data'!K2:K601) -> 187955.95 | C7: =SUMIF('Raw Data'!F2:F601,A7,'Raw Data'!N2:N601) -> 24763.8

Sheet Q2 - Revenue by Category
A1: Q2: Which Categories Generate the Most Revenue
A3: Category | B3: Total Sales
A4: Furniture | B4: =SUMIF('Raw Data'!I2:I601,A4,'Raw Data'!K2:K601) -> 252148.24
A5: Office Supplies | B5: =SUMIF('Raw Data'!I2:I601,A5,'Raw Data'!K2:K601) -> 22620.16
A6: Technology | B6: =SUMIF('Raw Data'!I2:I601,A6,'Raw Data'!K2:K601) -> 655596.34

Sheet Q3 - Top Customers
A1: Q3: Top 10 Customers by Sales
A3: Customer Name | B3: Total Sales
A4: Patricia Martinez | B4: =SUMIF('Raw Data'!D2:D601,A4,'Raw Data'!K2:K601) -> 26224.74
A5: Patricia Lopez | B5: =SUMIF('Raw Data'!D2:D601,A5,'Raw Data'!K2:K601) -> 23607.12
A6: Karen Williams | B6: =SUMIF('Raw Data'!D2:D601,A6,'Raw Data'!K2:K601) -> 21350.6
A7: Joseph Taylor | B7: =SUMIF('Raw Data'!D2:D601,A7,'Raw Data'!K2:K601) -> 20928.79
A8: Mark Taylor | B8: =SUMIF('Raw Data'!D2:D601,A8,'Raw Data'!K2:K601) -> 20915.1
A9: Joseph Smith | B9: =SUMIF('Raw Data'!D2:D601,A9,'Raw Data'!K2:K601) -> 20533.04
A10: Thomas Thomas | B10: =SUMIF('Raw Data'!D2:D601,A10,'Raw Data'!K2:K601) -> 19328.05
A11: Sarah Garcia | B11: =SUMIF('Raw Data'!D2:D601,A11,'Raw Data'!K2:K601) -> 18435.7
A12: Michael Davis | B12: =SUMIF('Raw Data'!D2:D601,A12,'Raw Data'!K2:K601) -> 18354.9
A13: Susan Miller | B13: =SUMIF('Raw Data'!D2:D601,A13,'Raw Data'!K2:K601) -> 18124.5

Sheet Q4 - Monthly Trend
A1: Q4: How Sales Trend Month by Month
A3: Month | B3: Total Sales
A4: Jan-2024 | B4: =SUMIF('Raw Data'!O2:O601,A4,'Raw Data'!K2:K601) -> 20060.39
A5: Feb-2024 | B5: =SUMIF('Raw Data'!O2:O601,A5,'Raw Data'!K2:K601) -> 55738.62
A6: Mar-2024 | B6: =SUMIF('Raw Data'!O2:O601,A6,'Raw Data'!K2:K601) -> 46552.22
A7: Apr-2024 | B7: =SUMIF('Raw Data'!O2:O601,A7,'Raw Data'!K2:K601) -> 62287.07
A8: May-2024 | B8: =SUMIF('Raw Data'!O2:O601,A8,'Raw Data'!K2:K601) -> 49574.12
A9: Jun-2024 | B9: =SUMIF('Raw Data'!O2:O601,A9,'Raw Data'!K2:K601) -> 37559.33
A10: Jul-2024 | B10: =SUMIF('Raw Data'!O2:O601,A10,'Raw Data'!K2:K601) -> 9719.22
A11: Aug-2024 | B11: =SUMIF('Raw Data'!O2:O601,A11,'Raw Data'!K2:K601) -> 22390.65
A12: Sep-2024 | B12: =SUMIF('Raw Data'!O2:O601,A12,'Raw Data'!K2:K601) -> 39278.42
A13: Oct-2024 | B13: =SUMIF('Raw Data'!O2:O601,A13,'Raw Data'!K2:K601) -> 39281.3
A14: Nov-2024 | B14: =SUMIF('Raw Data'!O2:O601,A14,'Raw Data'!K2:K601) -> 24426.49
A15: Dec-2024 | B15: =SUMIF('Raw Data'!O2:O601,A15,'Raw Data'!K2:K601) -> 52734.9
A16: Jan-2025 | B16: =SUMIF('Raw Data'!O2:O601,A16,'Raw Data'!K2:K601) -> 47970.98
A17: Feb-2025 | B17: =SUMIF('Raw Data'!O2:O601,A17,'Raw Data'!K2:K601) -> 18462.21
A18: Mar-2025 | B18: =SUMIF('Raw Data'!O2:O601,A18,'Raw Data'!K2:K601) -> 29657.77
A19: Apr-2025 | B19: =SUMIF('Raw Data'!O2:O601,A19,'Raw Data'!K2:K601) -> 37698.92
A20: May-2025 | B20: =SUMIF('Raw Data'!O2:O601,A20,'Raw Data'!K2:K601) -> 65873.46
A21: Jun-2025 | B21: =SUMIF('Raw Data'!O2:O601,A21,'Raw Data'!K2:K601) -> 37575.1
A22: Jul-2025 | B22: =SUMIF('Raw Data'!O2:O601,A22,'Raw Data'!K2:K601) -> 48400.5
A23: Aug-2025 | B23: =SUMIF('Raw Data'!O2:O601,A23,'Raw Data'!K2:K601) -> 24345.01
A24: Sep-2025 | B24: =SUMIF('Raw Data'!O2:O601,A24,'Raw Data'!K2:K601) -> 32843.9
A25: Oct-2025 | B25: =SUMIF('Raw Data'!O2:O601,A25,'Raw Data'!K2:K601) -> 36628.6
A26: Nov-2025 | B26: =SUMIF('Raw Data'!O2:O601,A26,'Raw Data'!K2:K601) -> 51836.18
A27: Dec-2025 | B27: =SUMIF('Raw Data'!O2:O601,A27,'Raw Data'!K2:K601) -> 39469.38

Sheet Q5 - Profit Margin
A1: Q5: Sub-Categories with the Lowest Profit Margin
A3: Sub-Category | B3: Total Sales | C3: Total Profit | D3: Profit Margin
A4: Accessories | B4: =SUMIF('Raw Data'!J2:J601,A4,'Raw Data'!K2:K601) -> 40490.52 | C4: =SUMIF('Raw Data'!J2:J601,A4,'Raw Data'!N2:N601) -> 7667.83 | D4: =C4/B4 -> 0.18937346
A5: Art | B5: =SUMIF('Raw Data'!J2:J601,A5,'Raw Data'!K2:K601) -> 3799.77 | C5: =SUMIF('Raw Data'!J2:J601,A5,'Raw Data'!N2:N601) -> 770.29 | D5: =C5/B5 -> 0.20272016
A6: Binders | B6: =SUMIF('Raw Data'!J2:J601,A6,'Raw Data'!K2:K601) -> 3606.21 | C6: =SUMIF('Raw Data'!J2:J601,A6,'Raw Data'!N2:N601) -> 702.68 | D6: =C6/B6 -> 0.19485277
A7: Bookcases | B7: =SUMIF('Raw Data'!J2:J601,A7,'Raw Data'!K2:K601) -> 43458.43 | C7: =SUMIF('Raw Data'!J2:J601,A7,'Raw Data'!N2:N601) -> 1338.8 | D7: =C7/B7 -> 0.030806451
A8: Chairs | B8: =SUMIF('Raw Data'!J2:J601,A8,'Raw Data'!K2:K601) -> 67388.56 | C8: =SUMIF('Raw Data'!J2:J601,A8,'Raw Data'!N2:N601) -> 13334.62 | D8: =C8/B8 -> 0.19787661
A9: Copiers | B9: =SUMIF('Raw Data'!J2:J601,A9,'Raw Data'!K2:K601) -> 347086.78 | C9: =SUMIF('Raw Data'!J2:J601,A9,'Raw Data'!N2:N601) -> 63857.69 | D9: =C9/B9 -> 0.18398191
A10: Furnishings | B10: =SUMIF('Raw Data'!J2:J601,A10,'Raw Data'!K2:K601) -> 18937.23 | C10: =SUMIF('Raw Data'!J2:J601,A10,'Raw Data'!N2:N601) -> 3713.55 | D10: =C10/B10 -> 0.19609785
A11: Labels | B11: =SUMIF('Raw Data'!J2:J601,A11,'Raw Data'!K2:K601) -> 1004.5 | C11: =SUMIF('Raw Data'!J2:J601,A11,'Raw Data'!N2:N601) -> 192.97 | D11: =C11/B11 -> 0.19210553
A12: Machines | B12: =SUMIF('Raw Data'!J2:J601,A12,'Raw Data'!K2:K601) -> 183337.18 | C12: =SUMIF('Raw Data'!J2:J601,A12,'Raw Data'!N2:N601) -> 4491.78 | D12: =C12/B12 -> 0.024500104
A13: Paper | B13: =SUMIF('Raw Data'!J2:J601,A13,'Raw Data'!K2:K601) -> 3102.38 | C13: =SUMIF('Raw Data'!J2:J601,A13,'Raw Data'!N2:N601) -> 584.14 | D13: =C13/B13 -> 0.1882877
A14: Phones | B14: =SUMIF('Raw Data'!J2:J601,A14,'Raw Data'!K2:K601) -> 84681.86 | C14: =SUMIF('Raw Data'!J2:J601,A14,'Raw Data'!N2:N601) -> 15406.39 | D14: =C14/B14 -> 0.18193259
A15: Storage | B15: =SUMIF('Raw Data'!J2:J601,A15,'Raw Data'!K2:K601) -> 11107.3 | C15: =SUMIF('Raw Data'!J2:J601,A15,'Raw Data'!N2:N601) -> 2235.95 | D15: =C15/B15 -> 0.20130455
A16: Tables | B16: =SUMIF('Raw Data'!J2:J601,A16,'Raw Data'!K2:K601) -> 122364.02 | C16: =SUMIF('Raw Data'!J2:J601,A16,'Raw Data'!N2:N601) -> 2198.84 | D16: =C16/B16 -> 0.017969661
